hmmer_reader-0.0.14.dist-info/LICENSE.md
hmmer_reader-0.0.14.dist-info/zip-safe
hmmer_reader-0.0.14.dist-info/top_level.txt
hmmer_reader-0.0.14.dist-info/RECORD
hmmer_reader-0.0.14.dist-info/METADATA
hmmer_reader-0.0.14.dist-info/entry_points.txt
hmmer_reader-0.0.14.dist-info/WHEEL
hmmer_reader/_testit.py
hmmer_reader/meta_read.h
hmmer_reader/_version.py
hmmer_reader/_misc.py
hmmer_reader/_click.py
hmmer_reader/meta_read.c
hmmer_reader/_cli.py
hmmer_reader/__init__.py
hmmer_reader/_ffi.abi3.so
hmmer_reader/_reader.py
hmmer_reader/data/A0ALD9.fasta
hmmer_reader/data/three-profs.hmm.gz
hmmer_reader/data/corrupted1.hmm.gz
hmmer_reader/data/PF02545.hmm.gz
hmmer_reader/data/corrupted2.hmm.gz
hmmer_reader/data/PF02545.hmm.br.corrupted
hmmer_reader/data/corrupted3.hmm.gz
hmmer_reader/data/2OG-FeII_Oxy_3-nt.hmm.gz
hmmer_reader/data/__init__.py
hmmer_reader/test/test_reader.py
hmmer_reader/test/test_cli.py
hmmer_reader/test/__init__.py
