Metadata-Version: 2.1
Name: hmmer-reader
Version: 0.0.14
Summary: HMMER file reader
Home-page: https://github.com/EBI-Metagenomics/hmmer-reader-py
Author: Danilo Horta
Author-email: horta@ebi.ac.uk
Maintainer: Danilo Horta
Maintainer-email: horta@ebi.ac.uk
License: MIT
Download-URL: https://github.com/EBI-Metagenomics/hmmer-reader-py
Keywords: hmmer,reader
Platform: Windows
Platform: MacOS
Platform: Linux
Classifier: Development Status :: 5 - Production/Stable
Classifier: License :: OSI Approved :: MIT License
Classifier: Operating System :: OS Independent
Classifier: Programming Language :: Python
Requires-Dist: cffi (>=1.14.2)
Requires-Dist: click (>=7.0.0)
Requires-Dist: importlib-resources (>=1.4.0)
Requires-Dist: pandas (>=1.1.3)
Requires-Dist: pytest (>=5.3.5)
